polymcp/__init__.py
polymcp/mcp_stdio_client.py
polymcp/version.py
polymcp/cli/__init__.py
polymcp/cli/__main__.py
polymcp/cli/main.py
polymcp/cli/commands/__init__.py
polymcp/cli/commands/agent.py
polymcp/cli/commands/config.py
polymcp/cli/commands/init.py
polymcp/cli/commands/inspector.py
polymcp/cli/commands/server.py
polymcp/cli/commands/skills.py
polymcp/cli/commands/test.py
polymcp/cli/utils/__init__.py
polymcp/cli/utils/config.py
polymcp/cli/utils/registry.py
polymcp/cli/utils/validation.py
polymcp/inspector/__init__.py
polymcp/inspector/server.py
polymcp/inspector/static/index.html
polymcp/polyagent/__init__.py
polymcp/polyagent/agent.py
polymcp/polyagent/codemode_agent.py
polymcp/polyagent/llm_providers.py
polymcp/polyagent/skill_generator.py
polymcp/polyagent/skill_loader.py
polymcp/polyagent/skill_matcher.py
polymcp/polyagent/unified_agent.py
polymcp/polymcp_toolkit/__init__.py
polymcp/polymcp_toolkit/expose.py
polymcp/polymcp_toolkit/expose_tools_stdio.py
polymcp/polymcp_toolkit/expose_tools_wasm.py
polymcp/polymcp_toolkit/mcp_auth.py
polymcp/sandbox/__init__.py
polymcp/sandbox/docker_executor.py
polymcp/sandbox/executor.py
polymcp/sandbox/tools_api.py
polymcp/tools/advances_tools.py
polymcp/tools/auth_server.py
polymcp/tools/summarize_tool.py
polymcp-1.2.8.dist-info/licenses/LICENSE
polymcp-1.2.8.dist-info/METADATA
polymcp-1.2.8.dist-info/WHEEL
polymcp-1.2.8.dist-info/entry_points.txt
polymcp-1.2.8.dist-info/top_level.txt
polymcp-1.2.8.dist-info/RECORD
