Metadata-Version: 2.4
Name: polymcp
Version: 1.2.8
Summary: Universal MCP Agent & Toolkit for intelligent LLM tool orchestration
Author: PolyMCP
License: MIT
Project-URL: Homepage, https://github.com/llm-use/polymcp
Project-URL: Repository, https://github.com/llm-use/polymcp
Project-URL: Documentation, https://github.com/llm-use/polymcp#readme
Project-URL: Bug Tracker, https://github.com/llm-use/polymcp/issues
Keywords: mcp,llm,agent,ai,tools,orchestration
Classifier: Development Status :: 4 - Beta
Classifier: Intended Audience :: Developers
Classifier: License :: OSI Approved :: MIT License
Classifier: Programming Language :: Python :: 3
Classifier: Programming Language :: Python :: 3.8
Classifier: Programming Language :: Python :: 3.9
Classifier: Programming Language :: Python :: 3.10
Classifier: Programming Language :: Python :: 3.11
Classifier: Programming Language :: Python :: 3.12
Classifier: Topic :: Software Development :: Libraries :: Python Modules
Classifier: Topic :: Scientific/Engineering :: Artificial Intelligence
Requires-Python: >=3.8
License-File: LICENSE
Requires-Dist: fastapi>=0.109.0
Requires-Dist: uvicorn[standard]>=0.27.0
Requires-Dist: pydantic>=2.5.0
Requires-Dist: requests>=2.31.0
Requires-Dist: docstring-parser>=0.15
Requires-Dist: click>=8.1.0
Requires-Dist: rich>=13.7.0
Requires-Dist: jinja2>=3.1.0
Requires-Dist: pyyaml>=6.0.0
Requires-Dist: gitpython>=3.1.0
Requires-Dist: python-dotenv>=1.0.0
Requires-Dist: python-jose[cryptography]>=3.3.0
Requires-Dist: passlib[bcrypt]>=1.7.4
Requires-Dist: python-multipart>=0.0.6
Requires-Dist: docker>=7.0.0
Provides-Extra: openai
Requires-Dist: openai>=1.10.0; extra == "openai"
Provides-Extra: anthropic
Requires-Dist: anthropic>=0.8.0; extra == "anthropic"
Provides-Extra: all
Requires-Dist: openai>=1.10.0; extra == "all"
Requires-Dist: anthropic>=0.8.0; extra == "all"
Provides-Extra: production
Requires-Dist: sqlalchemy>=2.0.23; extra == "production"
Requires-Dist: redis>=5.0.1; extra == "production"
Requires-Dist: slowapi>=0.1.9; extra == "production"
Requires-Dist: alembic>=1.12.1; extra == "production"
Provides-Extra: dev
Requires-Dist: pytest>=7.4.0; extra == "dev"
Requires-Dist: pytest-asyncio>=0.23.0; extra == "dev"
Requires-Dist: pytest-cov>=4.1.0; extra == "dev"
Requires-Dist: black>=23.12.0; extra == "dev"
Requires-Dist: flake8>=7.0.0; extra == "dev"
Requires-Dist: mypy>=1.8.0; extra == "dev"
Requires-Dist: httpx>=0.26.0; extra == "dev"
Requires-Dist: build>=1.0.0; extra == "dev"
Requires-Dist: twine>=4.0.0; extra == "dev"
Dynamic: license-file
